odc/ui/__init__.py
odc/ui/_cmaps.py
odc/ui/_dc_explore.py
odc/ui/_images.py
odc/ui/_map.py
odc/ui/_ui.py
odc/ui/_version.py
odc/ui/plt_tools.py
odc_ui-0.2.1.dist-info/LICENSE
odc_ui-0.2.1.dist-info/METADATA
odc_ui-0.2.1.dist-info/WHEEL
odc_ui-0.2.1.dist-info/top_level.txt
odc_ui-0.2.1.dist-info/RECORD
