Metadata-Version: 2.1
Name: odc-ui
Version: 0.2.1
Summary: Notebook display helper methods
Home-page: https://github.com/opendatacube/odc-tools/
Author: Open Data Cube
Author-email: 
Maintainer: Open Data Cube
Maintainer-email: 
License: Apache License 2.0
Platform: any
Requires-Python: >=3.9
License-File: LICENSE
Requires-Dist: datacube
Requires-Dist: ipyleaflet
Requires-Dist: ipython
Requires-Dist: ipywidgets >=8.0
Requires-Dist: jupyter-ui-poll
Requires-Dist: matplotlib
Requires-Dist: numpy
Requires-Dist: odc-algo
Requires-Dist: pandas
Requires-Dist: rasterio
Requires-Dist: xarray
